LICENSE.txt
MANIFEST.in
README.rst
requirements.txt
setup.py
test_requirements.txt
cardano/__init__.py
cardano/consts.py
cardano/exceptions.py
cardano/metadata.py
cardano/numbers.py
cardano/simpletypes.py
cardano/transaction.py
cardano/wallet.py
cardano.egg-info/PKG-INFO
cardano.egg-info/SOURCES.txt
cardano.egg-info/dependency_links.txt
cardano.egg-info/requires.txt
cardano.egg-info/top_level.txt
cardano/address/__init__.py
cardano/address/bech32.py
cardano/address/shelley.py
cardano/backends/__init__.py
cardano/backends/walletrest/__init__.py
cardano/backends/walletrest/exceptions.py
cardano/backends/walletrest/serializers.py