Metadata-Version: 2.1
Name: cardano
Version: 0.8.2
Summary: Python module for handling Cardano cryptocurrency
Home-page: https://github.com/emesik/cardano-python/
Author: Michał Sałaban
Author-email: michal@salaban.info
License: BSD-3-Clause
Keywords: cardano cryptocurrency
Platform: UNKNOWN
Classifier: Development Status :: 4 - Beta
Classifier: Intended Audience :: Developers
Classifier: License :: OSI Approved :: BSD License
Classifier: Operating System :: OS Independent
Classifier: Programming Language :: Python
Classifier: Programming Language :: Python :: 3.6
Classifier: Programming Language :: Python :: 3.7
Classifier: Programming Language :: Python :: 3.8
Classifier: Programming Language :: Python :: 3.9
Classifier: Programming Language :: Python :: 3.10
Classifier: Topic :: Software Development :: Libraries :: Python Modules
License-File: LICENSE.txt
